mana_clust/__init__.py
mana_clust/common_functions.py
mana_clust/mana_annotate_results.py
mana_clust/mana_cat.py
mana_clust/mana_clust.py
mana_clust/mana_continuous.py
mana_clust/mana_log_loss.py
mana_clust/mana_make_website.py
mana_clust/run_simulation_study.py
mana_clust/simulate_datasets.py
MANAclust-0.7.3.dist-info/METADATA
MANAclust-0.7.3.dist-info/WHEEL
MANAclust-0.7.3.dist-info/top_level.txt
MANAclust-0.7.3.dist-info/RECORD
