Metadata-Version: 2.1
Name: MANAclust
Version: 0.7.3
Summary: Multi Affinity Network Association
Home-page: https://scottyler892@bitbucket.org/scottyler892/manaclust
Author: Scott Tyler
Author-email: scottyler89@gmail.com
Classifier: Programming Language :: Python :: 3
Classifier: License :: OSI Approved :: GNU Affero General Public License v3
Classifier: Operating System :: OS Independent
Requires-Dist: Pillow (>=5.4)
Requires-Dist: h5py (>=2.9.0)
Requires-Dist: ray
Requires-Dist: fastcluster
Requires-Dist: pandas
Requires-Dist: umap-learn (==0.3.10)
Requires-Dist: python-louvain
Requires-Dist: networkx (>=2.3)
Requires-Dist: seaborn (>=0.8.1)
Requires-Dist: numpy (>=1.16.0)
Requires-Dist: scikit-learn
Requires-Dist: matplotlib (>=3.0.2)
Requires-Dist: scipy (>=1.2.0)
